httpbinx-1.9.0.dist-info/METADATA
httpbinx-1.9.0.dist-info/WHEEL
httpbinx-1.9.0.dist-info/entry_points.txt
httpbinx-1.9.0.dist-info/licenses/LICENSE
httpbinx/__init__.py
httpbinx/cli.py
httpbinx/constants.py
httpbinx/examples/__init__.py
httpbinx/helpers.py
httpbinx/main.py
httpbinx/meta.py
httpbinx/routers/__init__.py
httpbinx/routers/anything.py
httpbinx/routers/auth.py
httpbinx/routers/cookies.py
httpbinx/routers/dynamicdata.py
httpbinx/routers/httpmethods.py
httpbinx/routers/images.py
httpbinx/routers/inspection/__init__.py
httpbinx/routers/inspection/request.py
httpbinx/routers/inspection/response.py
httpbinx/routers/redirects.py
httpbinx/routers/responseformats.py
httpbinx/routers/statuscodes.py
httpbinx/schemas.py
httpbinx/static/UTF-8-demo.txt
httpbinx/static/bombs/bomb-1GB.br
httpbinx/static/bombs/bomb-1GB.gz
httpbinx/static/favicon.png
httpbinx/static/images/httbinx_logo.png
httpbinx/static/images/httpbinx_cover.png
httpbinx/static/images/jackal.jpg
httpbinx/static/images/pig_icon.png
httpbinx/static/images/svg_logo.svg
httpbinx/static/images/wolf_1.webp
httpbinx/templates/moby.html
httpbinx/templates/sample.xml
httpbinx/templates/trackingscripts.html
httpbinx-1.9.0.dist-info/RECORD
