Metadata-Version: 2.1
Name: httpbinx
Version: 1.9.0
Summary: HTTP Request & Response Service, written in Python + FastAPI.
Author-Email: Leo <imleowoo@outlook.com>
Maintainer-Email: Leo <imleowoo@outlook.com>
License: MIT License
Classifier: Programming Language :: Python
Classifier: Programming Language :: Python :: 3
Classifier: Programming Language :: Python :: 3.9
Classifier: Programming Language :: Python :: 3.10
Classifier: Programming Language :: Python :: 3.11
Classifier: Programming Language :: Python :: 3.12
Classifier: Programming Language :: Python :: 3.13
Classifier: Programming Language :: Python :: 3.14
Classifier: License :: OSI Approved :: MIT License
Project-URL: Homepage, https://github.com/imleowoo/httpbinx
Project-URL: Repository, https://github.com/imleowoo/httpbinx
Requires-Python: >=3.8
Requires-Dist: fastapi
Requires-Dist: uvicorn
Requires-Dist: starlette
Requires-Dist: jinja2
Requires-Dist: brotli
Requires-Dist: python-multipart
Provides-Extra: test
Requires-Dist: httpx; extra == "test"
Requires-Dist: pytest-cov; extra == "test"
Requires-Dist: pytest-mock; extra == "test"
Requires-Dist: pytest-xdist; extra == "test"
Requires-Dist: pytest; extra == "test"
